pygip/__init__.py
pygip/datasets/__init__.py
pygip/datasets/datasets.py
pygip/models/__init__.py
pygip/models/attack/AdvMEA.py
pygip/models/attack/CEGA.py
pygip/models/attack/DataFreeMEA.py
pygip/models/attack/Realistic.py
pygip/models/attack/__init__.py
pygip/models/attack/base.py
pygip/models/attack/mea/MEA.py
pygip/models/attack/mea/__init__.py
pygip/models/attack/mea/data/attack2_generated_graph/citeseer/graph_label.txt
pygip/models/attack/mea/data/attack2_generated_graph/citeseer/query_labels.txt
pygip/models/attack/mea/data/attack2_generated_graph/citeseer/selected_index.txt
pygip/models/attack/mea/data/attack2_generated_graph/cora/graph_label.txt
pygip/models/attack/mea/data/attack2_generated_graph/cora/query_labels.txt
pygip/models/attack/mea/data/attack2_generated_graph/cora/selected_index.txt
pygip/models/attack/mea/data/attack2_generated_graph/pubmed/graph_label.txt
pygip/models/attack/mea/data/attack2_generated_graph/pubmed/query_labels.txt
pygip/models/attack/mea/data/attack2_generated_graph/pubmed/selected_index.txt
pygip/models/attack/mea/data/attack3_shadow_graph/citeseer/attack_6_sub_shadow_graph_index_attack_2.txt
pygip/models/attack/mea/data/attack3_shadow_graph/citeseer/attack_6_sub_shadow_graph_index_attack_3.txt
pygip/models/attack/mea/data/attack3_shadow_graph/citeseer/protential_1200_shadow_graph_index.txt
pygip/models/attack/mea/data/attack3_shadow_graph/citeseer/protential_1300_shadow_graph_index.txt
pygip/models/attack/mea/data/attack3_shadow_graph/citeseer/protential_500_shadow_graph_index.txt
pygip/models/attack/mea/data/attack3_shadow_graph/citeseer/protential_700_shadow_graph_index.txt
pygip/models/attack/mea/data/attack3_shadow_graph/citeseer/protential_900_shadow_graph_index.txt
pygip/models/attack/mea/data/attack3_shadow_graph/citeseer/target_graph_index.txt
pygip/models/attack/mea/data/attack3_shadow_graph/cora/attack_6_sub_shadow_graph_index_attack_2.txt
pygip-1.1.0.dist-info/licenses/LICENSE
pygip-1.1.0.dist-info/METADATA
pygip-1.1.0.dist-info/WHEEL
pygip-1.1.0.dist-info/top_level.txt
pygip-1.1.0.dist-info/RECORD
