Metadata-Version: 2.4
Name: PyGIP
Version: 1.1.0
Summary: A Python package for Graph Intellectual Property Protection
Author-email: Bolin Shen <blshen@fsu.edu>
License: BSD-2-Clause
Project-URL: Homepage, https://labrai.github.io/PyGIP
Project-URL: Repository, https://github.com/LabRAI/PyGIP
Classifier: Development Status :: 3 - Alpha
Classifier: Intended Audience :: Science/Research
Classifier: Topic :: Scientific/Engineering :: Artificial Intelligence
Classifier: License :: OSI Approved :: BSD License
Classifier: Programming Language :: Python :: 3.8
Classifier: Programming Language :: Python :: 3.9
Classifier: Programming Language :: Python :: 3.10
Classifier: Programming Language :: Python :: 3.11
Classifier: Programming Language :: Python :: 3.12
Classifier: Operating System :: OS Independent
Requires-Python: <3.13,>=3.8
License-File: LICENSE
Requires-Dist: torch-geometric>=2.0.0
Requires-Dist: numpy>=1.19.0
Requires-Dist: scipy>=1.6.0
Requires-Dist: networkx>=2.5
Requires-Dist: scikit-learn>=0.24.0
Requires-Dist: tqdm>=4.50.0
Requires-Dist: torchdata<0.8.0,>=0.7.0
Requires-Dist: pyyaml>=5.3.0
Requires-Dist: pydantic>=2.0.0
Provides-Extra: torch
Requires-Dist: torch==2.3.0; extra == "torch"
Provides-Extra: dgl
Requires-Dist: dgl==2.2.1; extra == "dgl"
Dynamic: license-file
